destlib/__init__.py
destlib/des.py
destlib/dst.py
destlib/time_units.py
destlib-1.1.2.dist-info/licenses/LICENSE
destlib-1.1.2.dist-info/METADATA
destlib-1.1.2.dist-info/WHEEL
destlib-1.1.2.dist-info/top_level.txt
destlib-1.1.2.dist-info/RECORD
