Metadata-Version: 2.4
Name: destlib
Version: 1.1.2
Summary: A Python library for Discrete Event and Stochastic Simulation
Home-page: https://github.com/PaleEXE/DESTlib
Author: Mohammad Al-Hennawi
Author-email: mohammed.alhennawi@gmail.com
License: MIT
Classifier: Programming Language :: Python :: 3
Classifier: License :: OSI Approved :: MIT License
Classifier: Operating System :: OS Independent
Requires-Python: >=3.8
License-File: LICENSE
Requires-Dist: pandas
Requires-Dist: matplotlib
Dynamic: author
Dynamic: author-email
Dynamic: classifier
Dynamic: description
Dynamic: description-content-type
Dynamic: home-page
Dynamic: license
Dynamic: license-file
Dynamic: requires-dist
Dynamic: requires-python
Dynamic: summary
